mugennoscraper/controller/helper.py
mugennoscraper/controller/router.py
mugennoscraper/controller/scrappers/rawkuma/const.py
mugennoscraper/controller/scrappers/rawkuma/handler.py
mugennoscraper/controller/scrappers/rawkuma/manga.py
mugennoscraper/controller/scrappers/rawkuma/page.py
mugennoscraper/controller/scrappers/rawkuma/search.py
mugennoscraper/model/chapter_page.py
mugennoscraper/model/interfaces.py
mugennoscraper/model/manga_page.py
mugennoscraper/model/search.py
mugennoscraper/model/search_page.py
mugennoscraper/utils/html.py
mugennoscraper-0.1.7.dist-info/METADATA
mugennoscraper-0.1.7.dist-info/WHEEL
mugennoscraper-0.1.7.dist-info/RECORD
