Metadata-Version: 2.3
Name: mugennoscraper
Version: 0.1.7
Summary: Manga Scraper for the Mugen Project.
License: GPLv3
Author: Kyamel
Author-email: lcamelo200@gmail.com
Requires-Python: >=3.12
Classifier: License :: Other/Proprietary License
Classifier: Programming Language :: Python :: 3
Classifier: Programming Language :: Python :: 3.12
Classifier: Programming Language :: Python :: 3.13
Requires-Dist: beautifulsoup4 (>=4.13.4,<5.0.0)
Requires-Dist: mugennocore (>=0.1.0,<0.2.0)
Requires-Dist: requests (>=2.32.3,<3.0.0)
